lightpack.py
py_lightpack-2.2.0.dist-info/METADATA
py_lightpack-2.2.0.dist-info/WHEEL
py_lightpack-2.2.0.dist-info/top_level.txt
py_lightpack-2.2.0.dist-info/RECORD
