Metadata-Version: 2.1
Name: py-lightpack
Version: 2.2.0
Summary: Library to control Lightpack
Home-page: https://github.com/tremby/py-lightpack
Author: Bart Nagel
Author-email: bart@tremby.net
License: GNU GPLv3
Platform: UNKNOWN
